backgroundtasks_cloud/__init__.py
backgroundtasks_cloud/core.py
backgroundtasks_cloud-0.1.0.dist-info/METADATA
backgroundtasks_cloud-0.1.0.dist-info/WHEEL
backgroundtasks_cloud-0.1.0.dist-info/top_level.txt
backgroundtasks_cloud-0.1.0.dist-info/RECORD
