Metadata-Version: 2.1
Name: backgroundtasks_cloud
Version: 0.1.0
Summary: A package for running background tasks in Python applications
Home-page: https://github.com/s-emanuilov/backgroundtasks
Author: Simeon Emanuilov
Author-email: Simeon Emanuilov <simeon.emanuilov@gmail.com>
Project-URL: Homepage, https://github.com/yourusername/backgroundtasks
Requires-Python: >=3.6
